MANIFEST.in
example.py
license
readme.rst
requirements.txt
setup.py
shorten/__init__.py
shorten/alphabets.py
shorten/base.py
shorten/errors.py
shorten/formatter.py
shorten/key.py
shorten/lock.py
shorten/memcache_store.py
shorten/memory_store.py
shorten/redis_store.py
shorten/token.py
shorten/version.py
shorten.egg-info/PKG-INFO
shorten.egg-info/SOURCES.txt
shorten.egg-info/dependency_links.txt
shorten.egg-info/requires.txt
shorten.egg-info/top_level.txt
tests/common.py
tests/test_bx.py
tests/test_memcache.py
tests/test_memory.py
tests/test_redis.py