Metadata-Version: 1.0
Name: shorten
Version: 2.0.2
Summary: A library for generating and storing short keys.
Home-page: https://github.com/tyrannosaur/shorten
Author: Charlie Liban
Author-email: charlie@tyrannosaur.ca
License: MIT License
Download-URL: https://github.com/tyrannosaur/shorten/zipball/master
Keywords: redis,memcached,internet,url,shortening
Platform: UNKNOWN
Classifier: Programming Language :: Python
Classifier: License :: OSI Approved :: MIT License
Classifier: Topic :: Internet :: WWW/HTTP
